{
  "players": [
    {
      "id": "4b608c17-eaca-49df-b336-49ecd0fc1923",
      "username": "rfandl",
      "firstName": "Ryan",
      "lastName": "Fandl",
      "wins": 1,
      "winsByWeek": [
        1
      ],
      "losses": 0,
      "lossesByWeek": [
        0
      ],
      "ties": 0,
      "tiesByWeek": [
        0
      ],
      "percent": 1,
      "points": 3,
      "pointsByWeek": [
        3
      ],
      "tbAvg": null,
      "tiebreakerByWeek": [
        45
      ],
      "lastWeekRank": 0,
      "currentWeekRank": 1,
      "rankByWeek": [
        1
      ],
      "change": "--",
      "currentWeekWins": 1,
      "currentWeekLosses": 0,
      "currentWeekTies": 0,
      "currentWeekPoints": 3,
      "currentWeekTiebreaker": 45,
      "survivorPicks": [
        "BAL"
      ],
      "aliveInSurvivor": true,
      "marginPicks": [
        {
          "team": "BAL",
          "margin": null
        }
      ],
      "marginTotal": 0,
      "highFiveValues": [
        1
      ],
      "highFiveTotal": 1,
      "highFiveThisWeek": [
        {
          "team": "KC",
          "won": true
        },
        {
          "team": "NO",
          "won": null
        },
        {
          "team": "IND",
          "won": null
        },
        {
          "team": "MIN",
          "won": null
        },
        {
          "team": "SF",
          "won": null
        }
      ]
    },
    {
      "id": "d9985b83-08de-4e96-bcbc-e348666a554c",
      "username": "Kfandl",
      "firstName": "Kailey",
      "lastName": "Fandl",
      "wins": 1,
      "winsByWeek": [
        1
      ],
      "losses": 0,
      "lossesByWeek": [
        0
      ],
      "ties": 0,
      "tiesByWeek": [
        0
      ],
      "percent": 1,
      "points": 1,
      "pointsByWeek": [
        1
      ],
      "tbAvg": null,
      "tiebreakerByWeek": [
        0
      ],
      "lastWeekRank": 0,
      "currentWeekRank": 2,
      "rankByWeek": [
        2
      ],
      "change": "--",
      "currentWeekWins": 1,
      "currentWeekLosses": 0,
      "currentWeekTies": 0,
      "currentWeekPoints": 1,
      "currentWeekTiebreaker": 0,
      "survivorPicks": [
        ""
      ],
      "aliveInSurvivor": true,
      "marginPicks": [
        {
          "team": "DET",
          "margin": -3
        }
      ],
      "marginTotal": -3,
      "highFiveValues": [
        0
      ],
      "highFiveTotal": 0,
      "highFiveThisWeek": [
        {
          "team": "N/A",
          "won": false
        },
        {
          "team": "N/A",
          "won": false
        },
        {
          "team": "N/A",
          "won": false
        },
        {
          "team": "N/A",
          "won": false
        },
        {
          "team": "N/A",
          "won": false
        }
      ]
    },
    {
      "id": "3cd5ef80-6348-407b-bd5c-6477f49c322e",
      "username": "Bcrimmins",
      "firstName": "Bobby",
      "lastName": "Crimmins",
      "wins": 0,
      "winsByWeek": [
        0
      ],
      "losses": 1,
      "lossesByWeek": [
        1
      ],
      "ties": 0,
      "tiesByWeek": [
        0
      ],
      "percent": 0,
      "points": 0,
      "pointsByWeek": [
        0
      ],
      "tbAvg": null,
      "tiebreakerByWeek": [
        0
      ],
      "lastWeekRank": 0,
      "currentWeekRank": 8,
      "rankByWeek": [
        8
      ],
      "change": "--",
      "currentWeekWins": 0,
      "currentWeekLosses": 1,
      "currentWeekTies": 0,
      "currentWeekPoints": 0,
      "currentWeekTiebreaker": 0,
      "survivorPicks": [
        ""
      ],
      "aliveInSurvivor": true,
      "marginPicks": [
        {
          "team": "DET",
          "margin": -3
        }
      ],
      "marginTotal": -3,
      "highFiveValues": [
        0
      ],
      "highFiveTotal": 0,
      "highFiveThisWeek": [
        {
          "team": "N/A",
          "won": false
        },
        {
          "team": "N/A",
          "won": false
        },
        {
          "team": "N/A",
          "won": false
        },
        {
          "team": "N/A",
          "won": false
        },
        {
          "team": "N/A",
          "won": false
        }
      ]
    },
    {
      "id": "11642444-4a38-42b3-8f2f-01b34bb50aef",
      "username": "hfandl23",
      "firstName": "Heather",
      "lastName": "Fandl",
      "wins": 1,
      "winsByWeek": [
        1
      ],
      "losses": 0,
      "lossesByWeek": [
        0
      ],
      "ties": 0,
      "tiesByWeek": [
        0
      ],
      "percent": 1,
      "points": 1,
      "pointsByWeek": [
        1
      ],
      "tbAvg": null,
      "tiebreakerByWeek": [
        0
      ],
      "lastWeekRank": 0,
      "currentWeekRank": 3,
      "rankByWeek": [
        3
      ],
      "change": "--",
      "currentWeekWins": 1,
      "currentWeekLosses": 0,
      "currentWeekTies": 0,
      "currentWeekPoints": 1,
      "currentWeekTiebreaker": 0,
      "survivorPicks": [
        ""
      ],
      "aliveInSurvivor": true,
      "marginPicks": [
        {
          "team": "DET",
          "margin": -3
        }
      ],
      "marginTotal": -3,
      "highFiveValues": [
        0
      ],
      "highFiveTotal": 0,
      "highFiveThisWeek": [
        {
          "team": "N/A",
          "won": false
        },
        {
          "team": "N/A",
          "won": false
        },
        {
          "team": "N/A",
          "won": false
        },
        {
          "team": "N/A",
          "won": false
        },
        {
          "team": "N/A",
          "won": false
        }
      ]
    },
    {
      "id": "0fd403ce-2a02-4c1e-8f47-be4facb1b18e",
      "username": "LaurScore25",
      "firstName": "Lauren",
      "lastName": "Almonte",
      "wins": 1,
      "winsByWeek": [
        1
      ],
      "losses": 0,
      "lossesByWeek": [
        0
      ],
      "ties": 0,
      "tiesByWeek": [
        0
      ],
      "percent": 1,
      "points": 1,
      "pointsByWeek": [
        1
      ],
      "tbAvg": null,
      "tiebreakerByWeek": [
        0
      ],
      "lastWeekRank": 0,
      "currentWeekRank": 4,
      "rankByWeek": [
        4
      ],
      "change": "--",
      "currentWeekWins": 1,
      "currentWeekLosses": 0,
      "currentWeekTies": 0,
      "currentWeekPoints": 1,
      "currentWeekTiebreaker": 0,
      "survivorPicks": [
        ""
      ],
      "aliveInSurvivor": true,
      "marginPicks": [
        {
          "team": "DET",
          "margin": -3
        }
      ],
      "marginTotal": -3,
      "highFiveValues": [
        0
      ],
      "highFiveTotal": 0,
      "highFiveThisWeek": [
        {
          "team": "N/A",
          "won": false
        },
        {
          "team": "N/A",
          "won": false
        },
        {
          "team": "N/A",
          "won": false
        },
        {
          "team": "N/A",
          "won": false
        },
        {
          "team": "N/A",
          "won": false
        }
      ]
    },
    {
      "id": "11c577d3-f0d5-4690-ab51-40aced33087d",
      "username": "aburd55",
      "firstName": "Andrew",
      "lastName": "Burdack",
      "wins": 1,
      "winsByWeek": [
        1
      ],
      "losses": 0,
      "lossesByWeek": [
        0
      ],
      "ties": 0,
      "tiesByWeek": [
        0
      ],
      "percent": 1,
      "points": 1,
      "pointsByWeek": [
        1
      ],
      "tbAvg": null,
      "tiebreakerByWeek": [
        0
      ],
      "lastWeekRank": 0,
      "currentWeekRank": 5,
      "rankByWeek": [
        5
      ],
      "change": "--",
      "currentWeekWins": 1,
      "currentWeekLosses": 0,
      "currentWeekTies": 0,
      "currentWeekPoints": 1,
      "currentWeekTiebreaker": 0,
      "survivorPicks": [
        ""
      ],
      "aliveInSurvivor": true,
      "marginPicks": [
        {
          "team": "DET",
          "margin": -3
        }
      ],
      "marginTotal": -3,
      "highFiveValues": [
        0
      ],
      "highFiveTotal": 0,
      "highFiveThisWeek": [
        {
          "team": "N/A",
          "won": false
        },
        {
          "team": "N/A",
          "won": false
        },
        {
          "team": "N/A",
          "won": false
        },
        {
          "team": "N/A",
          "won": false
        },
        {
          "team": "N/A",
          "won": false
        }
      ]
    },
    {
      "id": "02bee9d4-ea65-4930-801b-91eb457b39d1",
      "username": "Mcgovene",
      "firstName": "Neal",
      "lastName": "McGovern",
      "wins": 0,
      "winsByWeek": [
        0
      ],
      "losses": 1,
      "lossesByWeek": [
        1
      ],
      "ties": 0,
      "tiesByWeek": [
        0
      ],
      "percent": 0,
      "points": 0,
      "pointsByWeek": [
        0
      ],
      "tbAvg": null,
      "tiebreakerByWeek": [
        0
      ],
      "lastWeekRank": 0,
      "currentWeekRank": 9,
      "rankByWeek": [
        9
      ],
      "change": "--",
      "currentWeekWins": 0,
      "currentWeekLosses": 1,
      "currentWeekTies": 0,
      "currentWeekPoints": 0,
      "currentWeekTiebreaker": 0,
      "survivorPicks": [
        ""
      ],
      "aliveInSurvivor": true,
      "marginPicks": [
        {
          "team": "DET",
          "margin": -3
        }
      ],
      "marginTotal": -3,
      "highFiveValues": [
        0
      ],
      "highFiveTotal": 0,
      "highFiveThisWeek": [
        {
          "team": "N/A",
          "won": false
        },
        {
          "team": "N/A",
          "won": false
        },
        {
          "team": "N/A",
          "won": false
        },
        {
          "team": "N/A",
          "won": false
        },
        {
          "team": "N/A",
          "won": false
        }
      ]
    },
    {
      "id": "1ca93cf7-e957-4cf5-9745-71b1018764fe",
      "username": "gfandl",
      "firstName": "Glen",
      "lastName": "Fandl",
      "wins": 1,
      "winsByWeek": [
        1
      ],
      "losses": 0,
      "lossesByWeek": [
        0
      ],
      "ties": 0,
      "tiesByWeek": [
        0
      ],
      "percent": 1,
      "points": 1,
      "pointsByWeek": [
        1
      ],
      "tbAvg": null,
      "tiebreakerByWeek": [
        0
      ],
      "lastWeekRank": 0,
      "currentWeekRank": 6,
      "rankByWeek": [
        6
      ],
      "change": "--",
      "currentWeekWins": 1,
      "currentWeekLosses": 0,
      "currentWeekTies": 0,
      "currentWeekPoints": 1,
      "currentWeekTiebreaker": 0,
      "survivorPicks": [
        ""
      ],
      "aliveInSurvivor": true,
      "marginPicks": [
        {
          "team": "DET",
          "margin": -3
        }
      ],
      "marginTotal": -3,
      "highFiveValues": [
        0
      ],
      "highFiveTotal": 0,
      "highFiveThisWeek": [
        {
          "team": "N/A",
          "won": false
        },
        {
          "team": "N/A",
          "won": false
        },
        {
          "team": "N/A",
          "won": false
        },
        {
          "team": "N/A",
          "won": false
        },
        {
          "team": "N/A",
          "won": false
        }
      ]
    },
    {
      "id": "c142e306-509d-4735-a39d-1e29694504cf",
      "username": "linda104",
      "firstName": "Jackie",
      "lastName": "Cook",
      "wins": 1,
      "winsByWeek": [
        1
      ],
      "losses": 0,
      "lossesByWeek": [
        0
      ],
      "ties": 0,
      "tiesByWeek": [
        0
      ],
      "percent": 1,
      "points": 1,
      "pointsByWeek": [
        1
      ],
      "tbAvg": null,
      "tiebreakerByWeek": [
        0
      ],
      "lastWeekRank": 0,
      "currentWeekRank": 7,
      "rankByWeek": [
        7
      ],
      "change": "--",
      "currentWeekWins": 1,
      "currentWeekLosses": 0,
      "currentWeekTies": 0,
      "currentWeekPoints": 1,
      "currentWeekTiebreaker": 0,
      "survivorPicks": [
        ""
      ],
      "aliveInSurvivor": true,
      "marginPicks": [
        {
          "team": "DET",
          "margin": -3
        }
      ],
      "marginTotal": -3,
      "highFiveValues": [
        0
      ],
      "highFiveTotal": 0,
      "highFiveThisWeek": [
        {
          "team": "N/A",
          "won": false
        },
        {
          "team": "N/A",
          "won": false
        },
        {
          "team": "N/A",
          "won": false
        },
        {
          "team": "N/A",
          "won": false
        },
        {
          "team": "N/A",
          "won": false
        }
      ]
    },
    {
      "id": "ff856cea-b8cb-470e-91ec-0fb8149f7fdb",
      "username": "Hostiss",
      "firstName": "Matt",
      "lastName": "Ustas",
      "wins": 0,
      "winsByWeek": [
        0
      ],
      "losses": 1,
      "lossesByWeek": [
        1
      ],
      "ties": 0,
      "tiesByWeek": [
        0
      ],
      "percent": 0,
      "points": 0,
      "pointsByWeek": [
        0
      ],
      "tbAvg": null,
      "tiebreakerByWeek": [
        0
      ],
      "lastWeekRank": 0,
      "currentWeekRank": 10,
      "rankByWeek": [
        10
      ],
      "change": "--",
      "currentWeekWins": 0,
      "currentWeekLosses": 1,
      "currentWeekTies": 0,
      "currentWeekPoints": 0,
      "currentWeekTiebreaker": 0,
      "survivorPicks": [
        ""
      ],
      "aliveInSurvivor": true,
      "marginPicks": [
        {
          "team": "DET",
          "margin": -3
        }
      ],
      "marginTotal": -3,
      "highFiveValues": [
        0
      ],
      "highFiveTotal": 0,
      "highFiveThisWeek": [
        {
          "team": "N/A",
          "won": false
        },
        {
          "team": "N/A",
          "won": false
        },
        {
          "team": "N/A",
          "won": false
        },
        {
          "team": "N/A",
          "won": false
        },
        {
          "team": "N/A",
          "won": false
        }
      ]
    },
    {
      "id": "1c2c4e7e-c5b8-44a1-bf3a-dbf7449ddb14",
      "username": "Huep",
      "firstName": "Thomas",
      "lastName": "Passano",
      "wins": 0,
      "winsByWeek": [
        0
      ],
      "losses": 1,
      "lossesByWeek": [
        1
      ],
      "ties": 0,
      "tiesByWeek": [
        0
      ],
      "percent": 0,
      "points": 0,
      "pointsByWeek": [
        0
      ],
      "tbAvg": null,
      "tiebreakerByWeek": [
        0
      ],
      "lastWeekRank": 0,
      "currentWeekRank": 11,
      "rankByWeek": [
        11
      ],
      "change": "--",
      "currentWeekWins": 0,
      "currentWeekLosses": 1,
      "currentWeekTies": 0,
      "currentWeekPoints": 0,
      "currentWeekTiebreaker": 0,
      "survivorPicks": [
        ""
      ],
      "aliveInSurvivor": true,
      "marginPicks": [
        {
          "team": "DET",
          "margin": -3
        }
      ],
      "marginTotal": -3,
      "highFiveValues": [
        0
      ],
      "highFiveTotal": 0,
      "highFiveThisWeek": [
        {
          "team": "N/A",
          "won": false
        },
        {
          "team": "N/A",
          "won": false
        },
        {
          "team": "N/A",
          "won": false
        },
        {
          "team": "N/A",
          "won": false
        },
        {
          "team": "N/A",
          "won": false
        }
      ]
    }
  ]
}