{
  "teams": {
    "ARI": {
      "displayName": "Arizona",
      "wins": 3,
      "losses": 11,
      "ties": 0,
      "points_for": 259,
      "points_against": 376,
      "home_wins": 2,
      "home_losses": 5,
      "away_wins": 1,
      "away_losses": 6,
      "streak": "L1"
    },
    "ATL": {
      "displayName": "Atlanta",
      "wins": 6,
      "losses": 8,
      "ties": 0,
      "points_for": 258,
      "points_against": 278,
      "home_wins": 4,
      "home_losses": 3,
      "away_wins": 2,
      "away_losses": 5,
      "streak": "L2"
    },
    "BAL": {
      "displayName": "Baltimore",
      "wins": 11,
      "losses": 3,
      "ties": 0,
      "points_for": 384,
      "points_against": 225,
      "home_wins": 5,
      "home_losses": 2,
      "away_wins": 6,
      "away_losses": 1,
      "streak": "W4"
    },
    "BUF": {
      "displayName": "Buffalo",
      "wins": 8,
      "losses": 6,
      "ties": 0,
      "points_for": 345,
      "points_against": 288,
      "home_wins": 6,
      "home_losses": 2,
      "away_wins": 2,
      "away_losses": 4,
      "streak": "W2"
    },
    "CAR": {
      "displayName": "Carolina",
      "wins": 2,
      "losses": 12,
      "ties": 0,
      "points_for": 206,
      "points_against": 348,
      "home_wins": 2,
      "home_losses": 4,
      "away_wins": 0,
      "away_losses": 8,
      "streak": "W1"
    },
    "CHI": {
      "displayName": "Chicago",
      "wins": 5,
      "losses": 9,
      "ties": 0,
      "points_for": 287,
      "points_against": 329,
      "home_wins": 3,
      "home_losses": 3,
      "away_wins": 2,
      "away_losses": 6,
      "streak": "L1"
    },
    "CIN": {
      "displayName": "Cincinnati",
      "wins": 8,
      "losses": 6,
      "ties": 0,
      "points_for": 307,
      "points_against": 311,
      "home_wins": 5,
      "home_losses": 3,
      "away_wins": 3,
      "away_losses": 3,
      "streak": "W3"
    },
    "CLE": {
      "displayName": "Cleveland",
      "wins": 9,
      "losses": 5,
      "ties": 0,
      "points_for": 309,
      "points_against": 289,
      "home_wins": 7,
      "home_losses": 1,
      "away_wins": 2,
      "away_losses": 4,
      "streak": "W2"
    },
    "DAL": {
      "displayName": "Dallas",
      "wins": 10,
      "losses": 4,
      "ties": 0,
      "points_for": 431,
      "points_against": 264,
      "home_wins": 7,
      "home_losses": 0,
      "away_wins": 3,
      "away_losses": 4,
      "streak": "L1"
    },
    "DEN": {
      "displayName": "Denver",
      "wins": 7,
      "losses": 7,
      "ties": 0,
      "points_for": 304,
      "points_against": 351,
      "home_wins": 4,
      "home_losses": 3,
      "away_wins": 3,
      "away_losses": 4,
      "streak": "L1"
    },
    "DET": {
      "displayName": "Detroit",
      "wins": 10,
      "losses": 4,
      "ties": 0,
      "points_for": 382,
      "points_against": 331,
      "home_wins": 5,
      "home_losses": 2,
      "away_wins": 5,
      "away_losses": 2,
      "streak": "W1"
    },
    "GB": {
      "displayName": "Green Bay",
      "wins": 6,
      "losses": 8,
      "ties": 0,
      "points_for": 300,
      "points_against": 301,
      "home_wins": 4,
      "home_losses": 3,
      "away_wins": 2,
      "away_losses": 5,
      "streak": "L2"
    },
    "HOU": {
      "displayName": "Houston",
      "wins": 8,
      "losses": 6,
      "ties": 0,
      "points_for": 306,
      "points_against": 295,
      "home_wins": 5,
      "home_losses": 2,
      "away_wins": 3,
      "away_losses": 4,
      "streak": "W1"
    },
    "IND": {
      "displayName": "Indianapolis",
      "wins": 8,
      "losses": 6,
      "ties": 0,
      "points_for": 344,
      "points_against": 343,
      "home_wins": 3,
      "home_losses": 4,
      "away_wins": 5,
      "away_losses": 2,
      "streak": "W1"
    },
    "JAC": {
      "displayName": "Jacksonville",
      "wins": 8,
      "losses": 6,
      "ties": 0,
      "points_for": 319,
      "points_against": 313,
      "home_wins": 3,
      "home_losses": 5,
      "away_wins": 5,
      "away_losses": 1,
      "streak": "L3"
    },
    "KC": {
      "displayName": "Kansas City",
      "wins": 9,
      "losses": 5,
      "ties": 0,
      "points_for": 319,
      "points_against": 245,
      "home_wins": 4,
      "home_losses": 3,
      "away_wins": 5,
      "away_losses": 2,
      "streak": "W1"
    },
    "LAC": {
      "displayName": "LA Chargers",
      "wins": 5,
      "losses": 9,
      "ties": 0,
      "points_for": 303,
      "points_against": 345,
      "home_wins": 2,
      "home_losses": 5,
      "away_wins": 3,
      "away_losses": 4,
      "streak": "L2"
    },
    "LA": {
      "displayName": "LA Rams",
      "wins": 7,
      "losses": 7,
      "ties": 0,
      "points_for": 327,
      "points_against": 310,
      "home_wins": 4,
      "home_losses": 3,
      "away_wins": 3,
      "away_losses": 4,
      "streak": "W1"
    },
    "LV": {
      "displayName": "Las Vegas",
      "wins": 6,
      "losses": 8,
      "ties": 0,
      "points_for": 265,
      "points_against": 280,
      "home_wins": 5,
      "home_losses": 3,
      "away_wins": 1,
      "away_losses": 5,
      "streak": "W1"
    },
    "MIA": {
      "displayName": "Miami",
      "wins": 10,
      "losses": 4,
      "ties": 0,
      "points_for": 441,
      "points_against": 294,
      "home_wins": 6,
      "home_losses": 1,
      "away_wins": 4,
      "away_losses": 3,
      "streak": "W1"
    },
    "MIN": {
      "displayName": "Minnesota",
      "wins": 7,
      "losses": 7,
      "ties": 0,
      "points_for": 290,
      "points_against": 269,
      "home_wins": 2,
      "home_losses": 4,
      "away_wins": 5,
      "away_losses": 3,
      "streak": "L1"
    },
    "NE": {
      "displayName": "New England",
      "wins": 3,
      "losses": 11,
      "ties": 0,
      "points_for": 186,
      "points_against": 299,
      "home_wins": 1,
      "home_losses": 7,
      "away_wins": 2,
      "away_losses": 4,
      "streak": "L1"
    },
    "NO": {
      "displayName": "New Orleans",
      "wins": 7,
      "losses": 7,
      "ties": 0,
      "points_for": 309,
      "points_against": 267,
      "home_wins": 4,
      "home_losses": 3,
      "away_wins": 3,
      "away_losses": 4,
      "streak": "W2"
    },
    "NYG": {
      "displayName": "NY Giants",
      "wins": 5,
      "losses": 9,
      "ties": 0,
      "points_for": 189,
      "points_against": 338,
      "home_wins": 3,
      "home_losses": 3,
      "away_wins": 2,
      "away_losses": 6,
      "streak": "L1"
    },
    "NYJ": {
      "displayName": "NY Jets",
      "wins": 5,
      "losses": 9,
      "ties": 0,
      "points_for": 201,
      "points_against": 287,
      "home_wins": 3,
      "home_losses": 5,
      "away_wins": 2,
      "away_losses": 4,
      "streak": "L1"
    },
    "PHI": {
      "displayName": "Philadelphia",
      "wins": 10,
      "losses": 3,
      "ties": 0,
      "points_for": 342,
      "points_against": 321,
      "home_wins": 5,
      "home_losses": 1,
      "away_wins": 5,
      "away_losses": 2,
      "streak": "L2"
    },
    "PIT": {
      "displayName": "Pittsburgh",
      "wins": 7,
      "losses": 7,
      "ties": 0,
      "points_for": 223,
      "points_against": 280,
      "home_wins": 4,
      "home_losses": 4,
      "away_wins": 3,
      "away_losses": 3,
      "streak": "L3"
    },
    "SEA": {
      "displayName": "Seattle",
      "wins": 6,
      "losses": 7,
      "ties": 0,
      "points_for": 280,
      "points_against": 318,
      "home_wins": 4,
      "home_losses": 2,
      "away_wins": 2,
      "away_losses": 5,
      "streak": "L4"
    },
    "SF": {
      "displayName": "San Francisco",
      "wins": 11,
      "losses": 3,
      "ties": 0,
      "points_for": 425,
      "points_against": 234,
      "home_wins": 5,
      "home_losses": 1,
      "away_wins": 6,
      "away_losses": 2,
      "streak": "W6"
    },
    "TB": {
      "displayName": "Tampa Bay",
      "wins": 7,
      "losses": 7,
      "ties": 0,
      "points_for": 296,
      "points_against": 290,
      "home_wins": 3,
      "home_losses": 3,
      "away_wins": 4,
      "away_losses": 4,
      "streak": "W3"
    },
    "TEN": {
      "displayName": "Tennessee",
      "wins": 5,
      "losses": 9,
      "ties": 0,
      "points_for": 257,
      "points_against": 301,
      "home_wins": 4,
      "home_losses": 3,
      "away_wins": 1,
      "away_losses": 6,
      "streak": "L1"
    },
    "WAS": {
      "displayName": "Washington",
      "wins": 4,
      "losses": 10,
      "ties": 0,
      "points_for": 315,
      "points_against": 389,
      "home_wins": 1,
      "home_losses": 5,
      "away_wins": 3,
      "away_losses": 5,
      "streak": "L5"
    }
  }
}